CHANGELOG.md
LICENSE
MANIFEST.in
README.md
setup.cfg
setup.py
versioneer.py
src/libreflow/__init__.py
src/libreflow.pianoplayer.egg-info/PKG-INFO
src/libreflow.pianoplayer.egg-info/SOURCES.txt
src/libreflow.pianoplayer.egg-info/dependency_links.txt
src/libreflow.pianoplayer.egg-info/requires.txt
src/libreflow.pianoplayer.egg-info/top_level.txt
src/libreflow/pianoplayer/__init__.py
src/libreflow/pianoplayer/_version.py
src/libreflow/pianoplayer/gui.py
src/libreflow/pianoplayer/session.py
src/libreflow/pianoplayer/custom_home/__init__.py
src/libreflow/pianoplayer/custom_home/ui.py
src/libreflow/pianoplayer/flow/__init__.py
src/libreflow/pianoplayer/flow/compositing.py
src/libreflow/pianoplayer/flow/entity_manager.py
src/libreflow/pianoplayer/flow/export.py
src/libreflow/pianoplayer/flow/file.py
src/libreflow/pianoplayer/flow/film.py
src/libreflow/pianoplayer/flow/shotgrid.py
src/libreflow/pianoplayer/flow/site.py
src/libreflow/pianoplayer/flow/task.py
src/libreflow/pianoplayer/flow/unpacking.py
src/libreflow/pianoplayer/flow/users.py
src/libreflow/pianoplayer/flow/packaging/__init__.py
src/libreflow/pianoplayer/flow/packaging/actions.py
src/libreflow/pianoplayer/flow/packaging/package.py
src/libreflow/pianoplayer/resources/__init__.py
src/libreflow/pianoplayer/resources/file_templates/__init__.py
src/libreflow/pianoplayer/resources/file_templates/template.aep
src/libreflow/pianoplayer/resources/gui/__init__.py
src/libreflow/pianoplayer/resources/gui/styles/__init__.py
src/libreflow/pianoplayer/resources/gui/styles/custom_style/__init__.py
src/libreflow/pianoplayer/resources/gui/styles/custom_style/custom_style.css
src/libreflow/pianoplayer/resources/icons/__init__.py
src/libreflow/pianoplayer/resources/icons/flow/__init__.py
src/libreflow/pianoplayer/resources/icons/flow/shotgrid.png
src/libreflow/pianoplayer/resources/icons/gui/__init__.py
src/libreflow/pianoplayer/resources/icons/gui/anim-layers.png
src/libreflow/pianoplayer/resources/icons/gui/available.png
src/libreflow/pianoplayer/resources/icons/gui/error.png
src/libreflow/pianoplayer/resources/icons/gui/found.png
src/libreflow/pianoplayer/resources/icons/gui/not-found-gray.png
src/libreflow/pianoplayer/resources/icons/gui/not-found.png
