Metadata-Version: 2.1
Name: libreflow.pianoplayer
Version: 2.2.6.1
Summary: Tailor-made flow for a feature film production
Home-page: https://gitlab.com/lfs.coop/libreflow/libreflow.pianoplayer
Author: Baptiste Delos, Flavio Perez
Author-email: baptiste@les-fees-speciales.coop, flavio@lfs.coop
License: LGPLv3+
Keywords: kabaret cgwire kitsu gazu animation pipeline libreflow
Platform: UNKNOWN
Classifier: Programming Language :: Python :: 3
Classifier: Intended Audience :: Developers
Classifier: Intended Audience :: End Users/Desktop
Classifier: Intended Audience :: Information Technology
Classifier: License :: OSI Approved :: GNU Lesser General Public License v3 or later (LGPLv3+)
Classifier: Operating System :: OS Independent
Requires-Python: >=3.8
License-File: LICENSE
